odoo/addons/project_status/README.rst
odoo/addons/project_status/__init__.py
odoo/addons/project_status/__manifest__.py
odoo/addons/project_status/data/data.xml
odoo/addons/project_status/i18n/de.po
odoo/addons/project_status/i18n/es.po
odoo/addons/project_status/i18n/project_status.pot
odoo/addons/project_status/models/__init__.py
odoo/addons/project_status/models/project.py
odoo/addons/project_status/models/project_status.py
odoo/addons/project_status/security/ir.model.access.csv
odoo/addons/project_status/static/description/icon.png
odoo/addons/project_status/views/project.xml
odoo/addons/project_status/views/project_status.xml
odoo12_addon_project_status-12.0.1.1.1.dist-info/METADATA
odoo12_addon_project_status-12.0.1.1.1.dist-info/WHEEL
odoo12_addon_project_status-12.0.1.1.1.dist-info/top_level.txt
odoo12_addon_project_status-12.0.1.1.1.dist-info/RECORD
